nobias/__init__.py
nobias/audits.py
nobias/distributionshift.py
nobias/explanation.py
nobias-0.1.51.dist-info/METADATA
nobias-0.1.51.dist-info/WHEEL
nobias-0.1.51.dist-info/licenses/LICENSE
nobias-0.1.51.dist-info/RECORD
