Metadata-Version: 2.1
Name: nobias
Version: 0.1.51
Summary: A small example package
Project-URL: Homepage, https://github.com/nobias-project/nobias
Project-URL: Bug Tracker, https://github.com/nobias-project/nobiasissues
Author-email: Carlos Mougan <carmougan@gmail.com>
License: MIT License
License-File: LICENSE
Classifier: License :: OSI Approved :: MIT License
Classifier: Operating System :: OS Independent
Classifier: Programming Language :: Python :: 3
Requires-Python: >=3.7
